{"ica/ica-bi.qmd":[],"index.qmd":[],"bw/Exam2.qmd":[],"ica/ica-uni.qmd":[],"ica/ica-import.qmd":[],"bw/Exam1.qmd":[],"bw/bw-bi.qmd":[],"bw/bw-tri.qmd":[],"bw/exam1-summarysheets.qmd":[],"ica/ica-reshaping.qmd":[],"bw/bw-spatial.qmd":[],"ica/ica-spatial.qmd":[],"ica/Effective.qmd":["ajstarks","AlDatavizguy"],"bw/bw-uni.qmd":[],"ica/ica-data.qmd":[],"ica/ica-joining.qmd":[],"ica/ica-multi.qmd":[],"ica/ica-wrangling.qmd":[],"ica/ica-strings.qmd":[],"solo_project/solo.qmd":[],"bw/Exam2_summary_sheet.qmd":[],"bw/bw-quad.qmd":[]}
